cupdate
